README.rst
setup.py
sshadduser.py
sshadduser.egg-info/PKG-INFO
sshadduser.egg-info/SOURCES.txt
sshadduser.egg-info/dependency_links.txt
sshadduser.egg-info/entry_points.txt
sshadduser.egg-info/requires.txt
sshadduser.egg-info/top_level.txt