Metadata-Version: 1.2
Name: sshadduser
Version: 1.0
Summary: 1-step to create user with SSH keys
Home-page: https://github.com/TeamHG-Memex/sshadduser
Author: Mark E. Haase
Author-email: mehaase@gmail.com
License: MIT
Keywords: open ssh add user authorized keys
Platform: UNKNOWN
Classifier: Development Status :: 5 - Production/Stable
Classifier: Environment :: Console
Classifier: Intended Audience :: Developers
Classifier: License :: OSI Approved :: MIT License
Classifier: Operating System :: POSIX
Classifier: Programming Language :: Python :: 3 :: Only
Classifier: Topic :: Utilities
Requires-Python: >=3
